pyaps3/__init__.py
pyaps3/autoget.py
pyaps3/delay.py
pyaps3/ecmwf.py
pyaps3/ecmwfapi.py
pyaps3/era.py
pyaps3/getaps.py
pyaps3/merra.py
pyaps3/model.cfg
pyaps3/narr.py
pyaps3/objects.py
pyaps3/processor.py
pyaps3/utils.py
pyaps3/newapi/example.py
pyaps3/newapi/setup.py
pyaps3/newapi/ecmwfapi/__init__.py
pyaps3/newapi/ecmwfapi/api.py
pyaps3-0.3.7.dist-info/licenses/LICENSE
pyaps3-0.3.7.dist-info/METADATA
pyaps3-0.3.7.dist-info/WHEEL
pyaps3-0.3.7.dist-info/top_level.txt
pyaps3-0.3.7.dist-info/RECORD
