Metadata-Version: 2.4
Name: pyaps3
Version: 0.3.7
Summary: Python based Atmospheric Phase Screen estimation
Author: Angelique Benoit
Author-email: Romain Jolivet <insar@geologie.ens.fr>
License: GPL-3.0-or-later
Project-URL: Homepage, https://github.com/insarlab/PyAPS
Project-URL: Issues, https://github.com/insarlab/PyAPS/issues
Keywords: InSAR,troposphere,geodesy,geophysics,ERA5
Classifier: Development Status :: 4 - Beta
Classifier: Intended Audience :: Science/Research
Classifier: Topic :: Scientific/Engineering
Classifier: License :: OSI Approved :: GNU General Public License v3 or later (GPLv3+)
Classifier: Operating System :: OS Independent
Classifier: Programming Language :: Python :: 3
Requires-Python: >=3.8
License-File: LICENSE
Requires-Dist: cdsapi>=0.7.2
Requires-Dist: numpy
Requires-Dist: pygrib
Requires-Dist: scipy
Requires-Dist: urllib3
Provides-Extra: test
Requires-Dist: matplotlib; extra == "test"
Requires-Dist: pip; extra == "test"
Requires-Dist: setuptools; extra == "test"
Requires-Dist: setuptools_scm; extra == "test"
Requires-Dist: wheel; extra == "test"
Dynamic: license-file
